fast_web_core/__init__.py
fast_web_core/auth/__init__.py
fast_web_core/auth/auth_cache_pool.py
fast_web_core/auth/share_auth.py
fast_web_core/client/__init__.py
fast_web_core/client/async_mongo_client.py
fast_web_core/client/async_mulit_tenant_mongo_client.py
fast_web_core/client/async_multi_database_mongo_client.py
fast_web_core/client/async_rabbit_client.py
fast_web_core/client/async_redis_client.py
fast_web_core/client/mongo_client.py
fast_web_core/client/multi_database_mongo_client.py
fast_web_core/client/multi_tenant_mongo_client.py
fast_web_core/client/oss2_client.py
fast_web_core/client/redis_client.py
fast_web_core/context/__init__.py
fast_web_core/context/context_vars.py
fast_web_core/exception/__init__.py
fast_web_core/exception/exceptions.py
fast_web_core/lib/__init__.py
fast_web_core/lib/cfg.py
fast_web_core/lib/func.py
fast_web_core/lib/logger.py
fast_web_core/lib/secret.py
fast_web_core/lib/settings.py
fast_web_core/lib/time.py
fast_web_core/lib/util.py
fast_web_core/middleware/__init__.py
fast_web_core/middleware/auth.py
fast_web_core/model/__init__.py
fast_web_core/model/base.py
fast_web_core/model/enums.py
fast_web_core/model/handler.py
fast_web_core/model/items.py
fast_web_core/model/query.py
fast_web_core/utils/__init__.py
fast_web_core/utils/common.py
fast_web_core/utils/context_var.py
fast_web_core/utils/decator.py
fast_web_core/utils/encryption.py
fast_web_core/utils/sequence.py
fast_web_core-1.0.2.dist-info/METADATA
fast_web_core-1.0.2.dist-info/WHEEL
fast_web_core-1.0.2.dist-info/top_level.txt
fast_web_core-1.0.2.dist-info/RECORD
