Metadata-Version: 2.1
Name: fast-web-core
Version: 1.0.2
Summary: fast web core for zsodata
Home-page: http://www.zsodata.com
Author: zsodata
Author-email: team@zso.io
License: BSD License
Platform: all
Requires-Python: >=3.7
